mcp_bigquery/__init__.py
mcp_bigquery/__main__.py
mcp_bigquery/bigquery_client.py
mcp_bigquery/cache.py
mcp_bigquery/config.py
mcp_bigquery/constants.py
mcp_bigquery/exceptions.py
mcp_bigquery/logging_config.py
mcp_bigquery/server.py
mcp_bigquery/sql_analyzer.py
mcp_bigquery/types.py
mcp_bigquery/utils.py
mcp_bigquery/validators.py
mcp_bigquery/clients/__init__.py
mcp_bigquery/clients/factory.py
mcp_bigquery/info_schema/__init__.py
mcp_bigquery/info_schema/_templates.py
mcp_bigquery/info_schema/performance.py
mcp_bigquery/info_schema/queries.py
mcp_bigquery/schema_explorer/__init__.py
mcp_bigquery/schema_explorer/_formatters.py
mcp_bigquery/schema_explorer/datasets.py
mcp_bigquery/schema_explorer/describe.py
mcp_bigquery/schema_explorer/tables.py
mcp_bigquery-0.4.2.dist-info/METADATA
mcp_bigquery-0.4.2.dist-info/WHEEL
mcp_bigquery-0.4.2.dist-info/entry_points.txt
mcp_bigquery-0.4.2.dist-info/licenses/LICENSE
mcp_bigquery-0.4.2.dist-info/RECORD
