Metadata-Version: 2.4
Name: mcp-bigquery
Version: 0.4.2
Summary: Minimal MCP server for BigQuery SQL validation and dry-run analysis
Project-URL: Homepage, https://github.com/caron14/mcp-bigquery
Project-URL: Documentation, https://github.com/caron14/mcp-bigquery#readme
Project-URL: Repository, https://github.com/caron14/mcp-bigquery.git
Project-URL: Issues, https://github.com/caron14/mcp-bigquery/issues
Author-email: caron14 <caron14@users.noreply.github.com>
Maintainer-email: caron14 <caron14@users.noreply.github.com>
License: MIT
License-File: LICENSE
Keywords: bigquery,claude,dry-run,gcp,mcp,sql,validation
Classifier: Development Status :: 4 - Beta
Classifier: Intended Audience :: Developers
Classifier: License :: OSI Approved :: MIT License
Classifier: Programming Language :: Python :: 3
Classifier: Programming Language :: Python :: 3.10
Classifier: Programming Language :: Python :: 3.11
Classifier: Programming Language :: Python :: 3.12
Classifier: Topic :: Database
Classifier: Topic :: Software Development :: Libraries :: Python Modules
Requires-Python: >=3.10
Requires-Dist: google-cloud-bigquery>=3.0.0
Requires-Dist: mcp>=1.0.0
Requires-Dist: pydantic>=2.0.0
Requires-Dist: sqlparse>=0.4.0
Requires-Dist: tabulate>=0.9.0
Provides-Extra: dev
Requires-Dist: black>=23.0.0; extra == 'dev'
Requires-Dist: build>=1.0.0; extra == 'dev'
Requires-Dist: mypy>=1.5.0; extra == 'dev'
Requires-Dist: pre-commit>=3.5.0; extra == 'dev'
Requires-Dist: pytest-asyncio>=0.21.0; extra == 'dev'
Requires-Dist: pytest>=7.0.0; extra == 'dev'
Requires-Dist: ruff>=0.1.0; extra == 'dev'
Requires-Dist: twine>=4.0.0; extra == 'dev'
